LICENSE
MANIFEST.in
README.md
package.json
setup.py
eqi_dash_chakra_ui/AspectRatio.py
eqi_dash_chakra_ui/Box.py
eqi_dash_chakra_ui/Center.py
eqi_dash_chakra_ui/ChakraProvider.py
eqi_dash_chakra_ui/Container.py
eqi_dash_chakra_ui/EqiDashChakraUi.py
eqi_dash_chakra_ui/Grid.py
eqi_dash_chakra_ui/GridItem.py
eqi_dash_chakra_ui/Icons.py
eqi_dash_chakra_ui/Table.py
eqi_dash_chakra_ui/__init__.py
eqi_dash_chakra_ui/_imports_.py
eqi_dash_chakra_ui/eqiFormControl.py
eqi_dash_chakra_ui/eqiInput.py
eqi_dash_chakra_ui/eqiTable.py
eqi_dash_chakra_ui/eqiThemeProvider.py
eqi_dash_chakra_ui/eqi_dash_chakra_ui.min.js
eqi_dash_chakra_ui/eqi_dash_chakra_ui.min.js.map
eqi_dash_chakra_ui/metadata.json
eqi_dash_chakra_ui/package-info.json
eqi_dash_chakra_ui.egg-info/PKG-INFO
eqi_dash_chakra_ui.egg-info/SOURCES.txt
eqi_dash_chakra_ui.egg-info/dependency_links.txt
eqi_dash_chakra_ui.egg-info/top_level.txt
tests/test_usage.py