Metadata-Version: 2.1
Name: eqi-dash-chakra-ui
Version: 0.0.1
Summary: Chakra UI components for beautiful data products with Plotly Dash
Author: Igor Machado <igor.conceicao@eqi.com.br>
License: MIT
Classifier: Framework :: Dash
License-File: LICENSE
